adftestpy/__init__.py
adftestpy/helpers.py
adftestpy-0.3.0.dist-info/LICENSE
adftestpy-0.3.0.dist-info/METADATA
adftestpy-0.3.0.dist-info/WHEEL
adftestpy-0.3.0.dist-info/top_level.txt
adftestpy-0.3.0.dist-info/RECORD
