Metadata-Version: 2.1
Name: adftestpy
Version: 0.3.0
Summary: Python library for running unit tests of Azure Data Factory configurations.
Home-page: UNKNOWN
Author: Ryan Brown
Author-email: ryanbrownnetworking777@gmail.com
License: MIT
Platform: UNKNOWN
Requires-Dist: pytest-runner
Requires-Dist: azure-identity
Requires-Dist: azure-mgmt-datafactory
